github_fast_downloader/__init__.py
github_fast_downloader/github_fast_downloader.py
github_fast_downloader-0.1.3.dist-info/METADATA
github_fast_downloader-0.1.3.dist-info/WHEEL
github_fast_downloader-0.1.3.dist-info/RECORD
