Metadata-Version: 2.4
Name: github-fast-downloader
Version: 0.1.3
Summary: A library for quickly retriving files and directories from GitHub reposities by utilizing git's sparse checkout feature.
Project-URL: homepage, https://github.com/stefanpie/github-fast-downloader
Project-URL: documentation, https://github.com/stefanpie/github-fast-downloader
Project-URL: repository, https://github.com/stefanpie/github-fast-downloader
Author-email: Stefan Abi-Karam <stefanabikaram@gatech.edu>
Requires-Python: >=3.11
